odoo/addons/mgmtsystem_action_efficacy/README.rst
odoo/addons/mgmtsystem_action_efficacy/__init__.py
odoo/addons/mgmtsystem_action_efficacy/__manifest__.py
odoo/addons/mgmtsystem_action_efficacy/i18n/it.po
odoo/addons/mgmtsystem_action_efficacy/i18n/mgmtsystem_action_efficacy.pot
odoo/addons/mgmtsystem_action_efficacy/models/__init__.py
odoo/addons/mgmtsystem_action_efficacy/models/mgmtsystem_action_efficacy.py
odoo/addons/mgmtsystem_action_efficacy/readme/CONFIGURE.rst
odoo/addons/mgmtsystem_action_efficacy/readme/CONTRIBUTORS.rst
odoo/addons/mgmtsystem_action_efficacy/readme/DESCRIPTION.rst
odoo/addons/mgmtsystem_action_efficacy/readme/HISTORY.rst
odoo/addons/mgmtsystem_action_efficacy/readme/INSTALL.rst
odoo/addons/mgmtsystem_action_efficacy/readme/ROADMAP.rst
odoo/addons/mgmtsystem_action_efficacy/readme/USAGE.rst
odoo/addons/mgmtsystem_action_efficacy/static/description/icon.png
odoo/addons/mgmtsystem_action_efficacy/static/description/index.html
odoo/addons/mgmtsystem_action_efficacy/tests/__init__.py
odoo/addons/mgmtsystem_action_efficacy/tests/test_action_efficacy.py
odoo/addons/mgmtsystem_action_efficacy/views/mgmtsystem_action_views.xml
odoo11_addon_mgmtsystem_action_efficacy-11.0.1.0.0.99.dev3.dist-info/METADATA
odoo11_addon_mgmtsystem_action_efficacy-11.0.1.0.0.99.dev3.dist-info/WHEEL
odoo11_addon_mgmtsystem_action_efficacy-11.0.1.0.0.99.dev3.dist-info/top_level.txt
odoo11_addon_mgmtsystem_action_efficacy-11.0.1.0.0.99.dev3.dist-info/RECORD
